pyqt_ani_button/__init__.py
pyqt_ani_button/aniButton.py
pyqt_ani_button-0.0.2.dist-info/LICENSE
pyqt_ani_button-0.0.2.dist-info/METADATA
pyqt_ani_button-0.0.2.dist-info/WHEEL
pyqt_ani_button-0.0.2.dist-info/top_level.txt
pyqt_ani_button-0.0.2.dist-info/RECORD
