Metadata-Version: 2.1
Name: pyqt-ani-button
Version: 0.0.2
Summary: PyQt QPushButton for animation
Home-page: https://github.com/yjg30737/pyqt-ani-button.git
Author: Jung Gyu Yoon
Author-email: yjg30737@gmail.com
License: MIT
Platform: UNKNOWN
License-File: LICENSE
Requires-Dist: PyQt5 (>=5.8)
Requires-Dist: pyqt-ani-abstractbutton (>=0.0.1)
